qtop/__init__.py
qtop/garbagecollector.py
qtop/tasks.py
qtop/utils.py
qtop/qtpy/__init__.py
qtop/qtpy/binding_helper.py
QPlug-1.0.1.dist-info/LICENSE
QPlug-1.0.1.dist-info/METADATA
QPlug-1.0.1.dist-info/WHEEL
QPlug-1.0.1.dist-info/top_level.txt
QPlug-1.0.1.dist-info/RECORD
