Metadata-Version: 2.1
Name: QPlug
Version: 1.0.1
Summary: Qt dependency for D-Analyst 
Home-page: https://github.com/Diachronic-Technologies/Qtop
Author: Agbakosi Adeoluwa(180 Memes), Diachronic Technologies
Author-email: adeoluwaagbakosi@gmail.com
License: UNKNOWN
Project-URL: Bug Tracker, https://github.com/Diachronic-Technologies/Qtop/issues
Platform: UNKNOWN
Classifier: Programming Language :: Python :: 3
Classifier: License :: OSI Approved :: MIT License
Classifier: Operating System :: OS Independent
Requires-Python: >=3.6
License-File: LICENSE
Requires-Dist: pyqt
